[
  {
    "url": "https://www.google.com/",
    "title": "Google ",
    "img": "/img/google.ico",
    "description": "Google 搜索  手气不错"
  },
  {
    "url": "https://www.github.com/",
    "title": "Github",
    "img": "/img/github.png",
    "description": "Where the world builds software · GitHub"
  },
  {
    "url": "https://fanyi.youdao.com/",
    "title": "在线翻译_有道",
    "img": "/img/youdao.ico",
    "description": "免费、即时的多语种在线翻译"
  },
  {
    "url": "https://spidertools.cn/#/",
    "title": "工具箱",
    "img": "/img/feapder.png",
    "description": "爬虫工具库"
  },
  {
    "url": "https://adminer.hjkl01.cn/",
    "title": "adminer",
    "img": "/img/adminer.ico",
    "description": "DB 可视化"
  },
  {
    "url": "https://jsonv.hjkl01.cn/editor/",
    "title": "JSON Valid",
    "img": "/img/jsonvalid.ico",
    "description": "Json视图"
  },
  {
    "url": "  https://gchq.github.io/CyberChef",
    "title": "加解密",
    "img": "/img/encryption.ico",
    "description": "a web app for encryption, encoding, compression and data analysis"
  },
  {
    "url": "https://curl.hjkl01.cn/",
    "title": "curl to python",
    "img": "/img/curl.ico",
    "description": "Convert curl commands to code"
  },
  {
    "url": "https://map.hjkl01.cn/",
    "title": "地图数据",
    "img": "/img/map.ico",
    "description": "fork"
  },
  {
    "url": "https://dber.hjkl01.cn/",
    "title": "Database design tool based on entity relation diagram",
    "img": "/img/dber.ico",
    "description": "fork"
  },
  {
    "url": "https://drf.hjkl01.cn/",
    "title": "drf中文文档",
    "img": "/img/drf.ico",
    "description": "fork"
  },
  {
    "url": "https://nginx.hjkl01.cn/",
    "title": "Nginx Online",
    "img": "/img/nginx.png",
    "description": "配置高性能、安全、稳定的NGINX服务器的最简单方法。"
  },
  {
    "url": "https://yacd.hjkl01.cn/",
    "title": "yacd",
    "img": "/img/yacd.ico",
    "description": "监测clash流量"
  }
]
